{
  "configs": [
    "implementation.xml",
    "global.xml",
    "api.xml"
  ],
  "secureProperties": [],
  "redeploymentEnabled": true,
  "name": "com.mycompany:emp-insight-api:1.0.0-SNAPSHOT",
  "minMuleVersion": "4.2.2",
  "requiredProduct": "MULE_EE",
  "classLoaderModelLoaderDescriptor": {
    "id": "mule",
    "attributes": {
      "exportedPackages": [],
      "exportedResources": [
        "api/api.raml",
        "api/dataTypes/emp-dataType.raml",
        "api/examples/400-error.json",
        "api/examples/500-error.json",
        "api/examples/list.json",
        "api/examples/req.json",
        "api/examples/res.json",
        "api/examples/score.json",
        "api.xml",
        "application-types.xml",
        "dwl/reUseableFunction.dwl",
        "global.xml",
        "implementation.xml",
        "log4j2.xml",
        "properties/app-DEV.properties",
        "properties/app-PROD.properties",
        "properties/app-SANDBOX.properties"
      ]
    }
  },
  "bundleDescriptorLoader": {
    "id": "mule",
    "attributes": {}
  }
}